language_world/__init__.py
language_world-0.1.1.dist-info/LICENSE
language_world-0.1.1.dist-info/METADATA
language_world-0.1.1.dist-info/WHEEL
language_world-0.1.1.dist-info/top_level.txt
language_world-0.1.1.dist-info/RECORD
