Metadata-Version: 2.1
Name: language_world
Version: 0.1.1
Summary: A robotics and language benchmark
Author-email: "K.R. Zentner" <krzentner@gmail.com>
License: MIT License
Project-URL: Homepage, https://github.com/krzentner/language-world
Project-URL: Bug Reports, https://github.com/krzentner/language-world/issues
Project-URL: Source, https://github.com/krzentner/language-world
Classifier: Development Status :: 3 - Alpha
Classifier: Intended Audience :: Science/Research
Classifier: License :: OSI Approved :: MIT License
Classifier: Programming Language :: Python :: 3
Classifier: Programming Language :: Python :: 3.7
Classifier: Programming Language :: Python :: 3.8
Classifier: Programming Language :: Python :: 3.9
Classifier: Programming Language :: Python :: 3.10
Classifier: Programming Language :: Python :: 3.11
Classifier: Programming Language :: Python :: 3 :: Only
Requires-Python: >=3.7
License-File: LICENSE
Requires-Dist: numpy >=1.22
